verilog_src/mac_q4_12.v
module mac_q4_12 (
    input wire signed [15:0] weight,
    input wire signed [15:0] in_val,
    input wire signed [15:0] acc_in,
    output reg signed [15:0] acc_out
);

    wire signed [31:0] product;

    assign product = weight * in_val;
    always @(*) begin
        acc_out = acc_in + product[27:12];
    end

endmodule

verilog_src/systolic_pe.v
`timescale 1ns / 1ps

module systolic_pe (
    input wire clk,
    input wire rst,
    input wire load_weight,
    input wire signed [15:0] weight_in,
    input wire signed [15:0] in_val_in,
    input wire signed [15:0] acc_in,

    output reg signed [15:0] weight_out,
    output reg signed [15:0] in_val_out,
    output reg signed [15:0] acc_out
);

    reg signed [15:0] stationary_weight;
    wire signed [15:0] mac_result;

    mac_q4_12 core_mac (
        .weight(stationary_weight),
        .in_val(in_val_in),
        .acc_in(acc_in),
        .acc_out(mac_result)
    );

    always @(posedge clk or posedge rst) begin
        if (rst) begin
            stationary_weight <= 16'd0;
            weight_out <= 16'd0;
            in_val_out <= 16'd0;
            acc_out    <= 16'd0;
        end else if (load_weight) begin
            stationary_weight <= weight_in;
            weight_out <= weight_in;
            in_val_out <= 16'd0;
            acc_out    <= 16'd0;
        end else begin
            in_val_out <= in_val_in;
            acc_out    <= mac_result;
        end
    end
endmodule

v1/verilog_src/tb_systolic_pe.v
`timescale 1ns / 1ps

module tb_systolic_pe;
    reg clk;
    reg rst;
    reg load_weight;
    reg signed [15:0] weight_in;
    reg signed [15:0] in_val_in;
    reg signed [15:0] acc_in;

    wire signed [15:0] weight_out;
    wire signed [15:0] in_val_out;
    wire signed [15:0] acc_out;

    reg signed [15:0] test_weights [0:99];
    reg signed [15:0] test_in_vals [0:99];
    reg signed [15:0] expected_outs [0:99];

    integer i;
    integer errors = 0;

    // Instantiate PE
    systolic_pe u_pe (
        .clk(clk),
        .rst(rst),
        .load_weight(load_weight),
        .weight_in(weight_in),
        .in_val_in(in_val_in),
        .acc_in(acc_in),
        .weight_out(weight_out),
        .in_val_out(in_val_out),
        .acc_out(acc_out)
    );

    // Clock generation (10ns period)
    initial begin
        clk = 0;
        forever #5 clk = ~clk;
    end

    initial begin
        // Waveform dump for debugging
        $dumpfile("tb_pe.vcd");
        $dumpvars(0, tb_systolic_pe);

        // Load vectors
        $readmemh("pe_weights.hex", test_weights);
        $readmemh("pe_in_vals.hex", test_in_vals);
        $readmemh("pe_expected_outs.hex", expected_outs);

        // Initialize inputs
        rst = 1;
        load_weight = 0;
        weight_in = 0;
        in_val_in = 0;
        acc_in = 0;

        $display("----------------------------------------");
        $display("Starting Cycle-Accurate PE Test...");
        $display("----------------------------------------");

        // Cycle 0: Reset pulse
        @(negedge clk);
        rst = 0;

        for (i = 0; i < 100; i = i + 1) begin
            // Progress marker
            if (i % 20 == 0) $display("  ...vector %0d", i);

            // Cycle 1: Load Phase
            @(negedge clk);
            load_weight = 1;
            weight_in = test_weights[i];
            in_val_in = 16'hDEAD; // Drive garbage to prove load flush works
            acc_in = 16'hBEEF;    // Drive garbage

            // Cycle 2: Compute Phase (Inputs presented)
            @(negedge clk);
            load_weight = 0;
            weight_in = 16'h0000;
            in_val_in = test_in_vals[i];
            acc_in = 16'd0; // Standalone PE, no accumulation

            // Cycle 3: Check Result (after rising edge has latched it)
            @(negedge clk);
            if (acc_out !== expected_outs[i]) begin
                $display("FAIL at vector %0d: W=%h, X=%h", i, test_weights[i], test_in_vals[i]);
                $display("  Expected %h, Got %h", expected_outs[i], acc_out);
                errors = errors + 1;
            end
        end

        $display("----------------------------------------");
        if (errors == 0)
            $display("PASS: PE Timing and Math verified for 100 cycles!");
        else
            $display("FAIL: %0d errors found.", errors);
        $display("----------------------------------------");

        $finish;
    end
endmodule

verilog_src/tb_pe.vcd
$date
	Wed Sep  9 14:06:10 2026
$end
$version
	Icarus Verilog
$end
$timescale
	1ps
$end
$scope module tb_systolic_pe $end
$var wire 16 ! weight_out [15:0] $end
$var wire 16 " in_val_out [15:0] $end
$var wire 16 # acc_out [15:0] $end
$var reg 16 $ acc_in [15:0] $end
$var reg 1 % clk $end
$var reg 16 & in_val_in [15:0] $end
$var reg 1 ' load_weight $end
$var reg 1 ( rst $end
$var reg 16 ) weight_in [15:0] $end
$var integer 32 * errors [31:0] $end
$var integer 32 + i [31:0] $end
$scope module u_pe $end
$var wire 16 , acc_in [15:0] $end
$var wire 1 % clk $end
$var wire 16 - in_val_in [15:0] $end
$var wire 1 ' load_weight $end
$var wire 1 ( rst $end
$var wire 16 . weight_in [15:0] $end
$var wire 16 / mac_result [15:0] $end
$var reg 16 0 acc_out [15:0] $end
$var reg 16 1 in_val_out [15:0] $end
$var reg 16 2 stationary_weight [15:0] $end
$var reg 16 3 weight_out [15:0] $end
$scope module core_mac $end
$var wire 16 4 acc_in [15:0] $end
$var wire 16 5 in_val [15:0] $end
$var wire 16 6 weight [15:0] $end
$var wire 32 7 product [31:0] $end
$var reg 16 8 acc_out [15:0] $end
$upscope $end
$upscope $end
$upscope $end
$enddefinitions $end
$comment Show the parameter values. $end
$dumpall
$end
#0
$dumpvars
b0 8
b0 7
b0 6
b0 5
b0 4
b0 3
b0 2
b0 1
b0 0
b0 /
b0 .
b0 -
b0 ,
bx +
b0 *
b0 )
1(
0'
b0 &
0%
b0 $
b0 #
b0 "
b0 !
$end
#5000
1%
#10000
b0 +
0(
0%
#15000
1%
#20000
b1011111011101111 /
b1011111011101111 8
b1011111011101111 $
b1011111011101111 ,
b1011111011101111 4
b1101111010101101 &
b1101111010101101 -
b1101111010101101 5
b10001110110001 )
b10001110110001 .
1'
0%
#25000
b111010010011000 /
b111010010011000 8
b10001110110001 !
b10001110110001 3
b11111011010110101001110010011101 7
b10001110110001 2
b10001110110001 6
1%
#30000
b1111000011000000 /
b1111000011000000 8
b0 $
b0 ,
b0 4
b11101111000011000000001000110111 7
b1000011001100111 &
b1000011001100111 -
b1000011001100111 5
b0 )
b0 .
0'
0%
#35000
b1111000011000000 #
b1111000011000000 0
b1000011001100111 "
b1000011001100111 1
1%
#40000
b1 +
0%
#45000
1%
#50000
b111010010011000 /
b111010010011000 8
b1011111011101111 $
b1011111011101111 ,
b1011111011101111 4
b11111011010110101001110010011101 7
b1101111010101101 &
b1101111010101101 -
b1101111010101101 5
b1100011001101000 )
b1100011001101000 .
1'
0%
#55000
b11011011100011 /
b11011011100011 8
b0 #
b0 0
b0 "
b0 1
b1100011001101000 !
b1100011001101000 3
b111011111110100010001001000 7
b1100011001101000 2
b1100011001101000 6
1%
#60000
b1111111100010000 /
b1111111100010000 8
b0 $
b0 ,
b0 4
b1111111100010000111010100000 7
b1011100100100100 &
b1011100100100100 -
b1011100100100100 5
b0 )
b0 .
0'
0%
#65000
b1111111100010000 #
b1111111100010000 0
b1011100100100100 "
b1011100100100100 1
1%
#70000
b10 +
0%
#75000
1%
#80000
b11011011100011 /
b11011011100011 8
b1011111011101111 $
b1011111011101111 ,
b1011111011101111 4
b111011111110100010001001000 7
b1101111010101101 &
b1101111010101101 -
b1101111010101101 5
b11110010001001 )
b11110010001001 .
1'
0%
#85000
b100000011011010 /
b100000011011010 8
b0 #
b0 0
b0 "
b0 1
b11110010001001 !
b11110010001001 3
b11111000000111101011011010010101 7
b11110010001001 2
b11110010001001 6
1%
#90000
b1010101100100100 /
b1010101100100100 8
b0 $
b0 ,
b0 4
b1010101100100100010100011100 7
b10110100111100 &
b10110100111100 -
b10110100111100 5
b0 )
b0 .
0'
0%
#95000
b1010101100100100 #
b1010101100100100 0
b10110100111100 "
b10110100111100 1
1%
#100000
b11 +
0%
#105000
1%
#110000
b100000011011010 /
b100000011011010 8
b1011111011101111 $
b1011111011101111 ,
b1011111011101111 4
b11111000000111101011011010010101 7
b1101111010101101 &
b1101111010101101 -
b1101111010101101 5
b110010001100101 )
b110010001100101 .
1'
0%
#115000
b1110110111010101 /
b1110110111010101 8
b0 #
b0 0
b0 "
b0 1
b110010001100101 !
b110010001100101 3
b11110010111011100110111001000001 7
b110010001100101 2
b110010001100101 6
1%
#120000
b110100010000001 /
b110100010000001 8
b0 $
b0 ,
b0 4
b11010110100010000001000000001010 7
b1001011001000010 &
b1001011001000010 -
b1001011001000010 5
b0 )
b0 .
0'
0%
#125000
b110100010000001 #
b110100010000001 0
b1001011001000010 "
b1001011001000010 1
1%
#130000
b100 +
0%
#135000
1%
#140000
b1110110111010101 /
b1110110111010101 8
b1011111011101111 $
b1011111011101111 ,
b1011111011101111 4
b11110010111011100110111001000001 7
b1101111010101101 &
b1101111010101101 -
b1101111010101101 5
b1110110000000011 )
b1110110000000011 .
1'
0%
#145000
b1110100010010000 /
b1110100010010000 8
b0 #
b0 0
b0 "
b0 1
b1110110000000011 !
b1110110000000011 3
b10100110100001100000000111 7
b1110110000000011 2
b1110110000000011 6
1%
#150000
b1001011001100000 /
b1001011001100000 8
b0 $
b0 ,
b0 4
b1001011001100000001011100011 7
b1000011110100001 &
b1000011110100001 -
b1000011110100001 5
b0 )
b0 .
0'
0%
#155000
b1001011001100000 #
b1001011001100000 0
b1000011110100001 "
b1000011110100001 1
1%
#160000
b101 +
0%
#165000
1%
#170000
b1110100010010000 /
b1110100010010000 8
b1011111011101111 $
b1011111011101111 ,
b1011111011101111 4
b10100110100001100000000111 7
b1101111010101101 &
b1101111010101101 -
b1101111010101101 5
b1011011111111000 )
b1011011111111000 .
1'
0%
#175000
b101010011110101 /
b101010011110101 8
b0 #
b0 0
b0 "
b0 1
b1011011111111000 !
b1011011111111000 3
b1001011000000110001010011000 7
b1011011111111000 2
b1011011111111000 6
1%
#180000
b1111100111011000 /
b1111100111011000 8
b0 $
b0 ,
b0 4
b11111111100111011000010100010000 7
b101011110 &
b101011110 -
b101011110 5
b0 )
b0 .
0'
0%
#185000
b1111100111011000 #
b1111100111011000 0
b101011110 "
b101011110 1
1%
#190000
b110 +
0%
#195000
1%
#200000
b101010011110101 /
b101010011110101 8
b1011111011101111 $
b1011111011101111 ,
b1011111011101111 4
b1001011000000110001010011000 7
b1101111010101101 &
b1101111010101101 -
b1101111010101101 5
b1000011011001011 )
b1000011011001011 .
1'
0%
#205000
b1011101101100001 /
b1011101101100001 8
b0 #
b0 0
b0 "
b0 1
b1000011011001011 !
b1000011011001011 3
b1111110001110010000100101111 7
b1000011011001011 2
b1000011011001011 6
1%
#210000
b100100000001100 /
b100100000001100 8
b0 $
b0 ,
b0 4
b100100100000001100011100101101 7
b1011001011100111 &
b1011001011100111 -
b1011001011100111 5
b0 )
b0 .
0'
0%
#215000
b100100000001100 #
b100100000001100 0
b1011001011100111 "
b1011001011100111 1
1%
#220000
b111 +
0%
#225000
1%
#230000
b1011101101100001 /
b1011101101100001 8
b1011111011101111 $
b1011111011101111 ,
b1011111011101111 4
b1111110001110010000100101111 7
b1101111010101101 &
b1101111010101101 -
b1101111010101101 5
b10011001011110 )
b10011001011110 .
1'
0%
#235000
b110111100000110 /
b110111100000110 8
b0 #
b0 0
b0 "
b0 1
b10011001011110 !
b10011001011110 3
b11111011000000010111000110000110 7
b10011001011110 2
b10011001011110 6
1%
#240000
b1101110010101 /
b1101110010101 8
b0 $
b0 ,
b0 4
b1101110010101111101011110 7
b101110000001 &
b101110000001 -
b101110000001 5
b0 )
b0 .
0'
0%
#245000
b1101110010101 #
b1101110010101 0
b101110000001 "
b101110000001 1
1%
#250000
b1000 +
0%
#255000
1%
#260000
b110111100000110 /
b110111100000110 8
b1011111011101111 $
b1011111011101111 ,
b1011111011101111 4
b11111011000000010111000110000110 7
b1101111010101101 &
b1101111010101101 -
b1101111010101101 5
b1011100001101111 )
b1011100001101111 .
1'
0%
#265000
b101001111111101 /
b101001111111101 8
b0 #
b0 0
b0 "
b0 1
b1011100001101111 !
b1011100001101111 3
b1001010100001110010100000011 7
b1011100001101111 2
b1011100001101111 6
1%
#270000
b1001100111001001 /
b1001100111001001 8
b0 $
b0 ,
b0 4
b11111001100111001001100010000110 7
b1011011011010 &
b1011011011010 -
b1011011011010 5
b0 )
b0 .
0'
0%
#275000
b1001100111001001 #
b1001100111001001 0
b1011011011010 "
b1011011011010 1
1%
#280000
b1001 +
0%
#285000
1%
#290000
b101001111111101 /
b101001111111101 8
b1011111011101111 $
b1011111011101111 ,
b1011111011101111 4
b1001010100001110010100000011 7
b1101111010101101 &
b1101111010101101 -
b1101111010101101 5
b100111100110110 )
b100111100110110 .
1'
0%
#295000
b1100111110100 /
b1100111110100 8
b0 #
b0 0
b0 "
b0 1
b100111100110110 !
b100111100110110 3
b11110101101100000101101101111110 7
b100111100110110 2
b100111100110110 6
1%
#300000
b1000111010001100 /
b1000111010001100 8
b0 $
b0 ,
b0 4
b11011000111010001100111111011100 7
b1000000110101010 &
b1000000110101010 -
b1000000110101010 5
b0 )
b0 .
0'
0%
#305000
b1000111010001100 #
b1000111010001100 0
b1000000110101010 "
b1000000110101010 1
1%
#310000
b1010 +
0%
#315000
1%
#320000
b1100111110100 /
b1100111110100 8
b1011111011101111 $
b1011111011101111 ,
b1011111011101111 4
b11110101101100000101101101111110 7
b1101111010101101 &
b1101111010101101 -
b1101111010101101 5
b100111001001001 )
b100111001001001 .
1'
0%
#325000
b1101111100010 /
b1101111100010 8
b0 #
b0 0
b0 "
b0 1
b100111001001001 !
b100111001001001 3
b11110101110011110011010101010101 7
b100111001001001 2
b100111001001001 6
1%
#330000
b1111100000101101 /
b1111100000101101 8
b0 $
b0 ,
b0 4
b1111100000101101010011000001 7
b11001010111001 &
b11001010111001 -
b11001010111001 5
b0 )
b0 .
0'
0%
#335000
b1111100000101101 #
b1111100000101101 0
b11001010111001 "
b11001010111001 1
1%
#340000
b1011 +
0%
#345000
1%
#350000
b1101111100010 /
b1101111100010 8
b1011111011101111 $
b1011111011101111 ,
b1011111011101111 4
b11110101110011110011010101010101 7
b1101111010101101 &
b1101111010101101 -
b1101111010101101 5
b1101011100011010 )
b1101011100011010 .
1'
0%
#355000
b1010000011101 /
b1010000011101 8
b0 #
b0 0
b0 "
b0 1
b1101011100011010 !
b1101011100011010 3
b101010100101110100010010010 7
b1101011100011010 2
b1101011100011010 6
1%
#360000
b1110000101110011 /
b1110000101110011 8
b0 $
b0 ,
b0 4
b1110000101110011010111010010 7
b1010011111001101 &
b1010011111001101 -
b1010011111001101 5
b0 )
b0 .
0'
0%
#365000
b1110000101110011 #
b1110000101110011 0
b1010011111001101 "
b1010011111001101 1
1%
#370000
b1100 +
0%
#375000
1%
#380000
b1010000011101 /
b1010000011101 8
b1011111011101111 $
b1011111011101111 ,
b1011111011101111 4
b101010100101110100010010010 7
b1101111010101101 &
b1101111010101101 -
b1101111010101101 5
b111010100001011 )
b111010100001011 .
1'
0%
#385000
b1100101100101001 /
b1100101100101001 8
b0 #
b0 0
b0 "
b0 1
b111010100001011 !
b111010100001011 3
b11110000110000111010001001101111 7
b111010100001011 2
b111010100001011 6
1%
#390000
b1100110111111101 /
b1100110111111101 8
b0 $
b0 ,
b0 4
b11101100110111111101101011011001 7
b1101011000101011 &
b1101011000101011 -
b1101011000101011 5
b0 )
b0 .
0'
0%
#395000
b1100110111111101 #
b1100110111111101 0
b1101011000101011 "
b1101011000101011 1
1%
#400000
b1101 +
0%
#405000
1%
#410000
b1100101100101001 /
b1100101100101001 8
b1011111011101111 $
b1011111011101111 ,
b1011111011101111 4
b11110000110000111010001001101111 7
b1101111010101101 &
b1101111010101101 -
b1101111010101101 5
b1001011110111110 )
b1001011110111110 .
1'
0%
#415000
b1001100000010011 /
b1001100000010011 8
b0 #
b0 0
b0 "
b0 1
b1001011110111110 !
b1001011110111110 3
b1101100100100100111101100110 7
b1001011110111110 2
b1001011110111110 6
1%
#420000
b1010000010111100 /
b1010000010111100 8
b0 $
b0 ,
b0 4
b101010000010111100110111111100 7
b1001100011000010 &
b1001100011000010 -
b1001100011000010 5
b0 )
b0 .
0'
0%
#425000
b1010000010111100 #
b1010000010111100 0
b1001100011000010 "
b1001100011000010 1
1%
#430000
b1110 +
0%
#435000
1%
#440000
b1001100000010011 /
b1001100000010011 8
b1011111011101111 $
b1011111011101111 ,
b1011111011101111 4
b1101100100100100111101100110 7
b1101111010101101 &
b1101111010101101 -
b1101111010101101 5
b101100011110101 )
b101100011110101 .
1'
0%
#445000
b10110101000 /
b10110101000 8
b0 #
b0 0
b0 "
b0 1
b101100011110101 !
b101100011110101 3
b11110100011010111001001110010001 7
b101100011110101 2
b101100011110101 6
1%
#450000
b1001001110011110 /
b1001001110011110 8
b0 $
b0 ,
b0 4
b1001001110011110000011110001 7
b1101010001101 &
b1101010001101 -
b1101010001101 5
b0 )
b0 .
0'
0%
#455000
b1001001110011110 #
b1001001110011110 0
b1101010001101 "
b1101010001101 1
1%
#460000
b1111 +
0%
#465000
1%
#470000
b10110101000 /
b10110101000 8
b1011111011101111 $
b1011111011101111 ,
b1011111011101111 4
b11110100011010111001001110010001 7
b1101111010101101 &
b1101111010101101 -
b1101111010101101 5
b100111010011111 )
b100111010011111 .
1'
0%
#475000
b1101100101111 /
b1101100101111 8
b0 #
b0 0
b0 "
b0 1
b100111010011111 !
b100111010011111 3
b11110101110001000000001101110011 7
b100111010011111 2
b100111010011111 6
1%
#480000
b10000011111001 /
b10000011111001 8
b0 $
b0 ,
b0 4
b10010000011111001100010010001 7
b11101011001111 &
b11101011001111 -
b11101011001111 5
b0 )
b0 .
0'
0%
#485000
b10000011111001 #
b10000011111001 0
b11101011001111 "
b11101011001111 1
1%
#490000
b10000 +
0%
#495000
1%
#500000
b1101100101111 /
b1101100101111 8
b1011111011101111 $
b1011111011101111 ,
b1011111011101111 4
b11110101110001000000001101110011 7
b1101111010101101 &
b1101111010101101 -
b1101111010101101 5
b100101000110 )
b100101000110 .
1'
0%
#505000
b1010101110011110 /
b1010101110011110 8
b0 #
b0 0
b0 "
b0 1
b100101000110 !
b100101000110 3
b11111110110010101111100001001110 7
b100101000110 2
b100101000110 6
1%
#510000
b100011000110010 /
b100011000110010 8
b0 $
b0 ,
b0 4
b100011000110010001011101110 7
b111100100011101 &
b111100100011101 -
b111100100011101 5
b0 )
b0 .
0'
0%
#515000
b100011000110010 #
b100011000110010 0
b111100100011101 "
b111100100011101 1
1%
#520000
b10001 +
0%
#525000
1%
#530000
b1010101110011110 /
b1010101110011110 8
b1011111011101111 $
b1011111011101111 ,
b1011111011101111 4
b11111110110010101111100001001110 7
b1101111010101101 &
b1101111010101101 -
b1101111010101101 5
b1110000011100111 )
b1110000011100111 .
1'
0%
#535000
b1111111110110011 /
b1111111110110011 8
b0 #
b0 0
b0 "
b0 1
b1110000011100111 !
b1110000011100111 3
b100000011000100111000011011 7
b1110000011100111 2
b1110000011100111 6
1%
#540000
b1110011000011100 /
b1110011000011100 8
b0 $
b0 ,
b0 4
b11111110011000011100010011111110 7
b110101010010 &
b110101010010 -
b110101010010 5
b0 )
b0 .
0'
0%
#545000
b1110011000011100 #
b1110011000011100 0
b110101010010 "
b110101010010 1
1%
#550000
b10010 +
0%
#555000
1%
#560000
b1111111110110011 /
b1111111110110011 8
b1011111011101111 $
b1011111011101111 ,
b1011111011101111 4
b100000011000100111000011011 7
b1101111010101101 &
b1101111010101101 -
b1101111010101101 5
b101010001010011 )
b101010001010011 .
1'
0%
#565000
b111101001110 /
b111101001110 8
b0 #
b0 0
b0 "
b0 1
b101010001010011 !
b101010001010011 3
b11110101000001011111011000010111 7
b101010001010011 2
b101010001010011 6
1%
#570000
b1001111111100110 /
b1001111111100110 8
b0 $
b0 ,
b0 4
b1001111111100110001000110101 7
b1111001010111 &
b1111001010111 -
b1111001010111 5
b0 )
b0 .
0'
0%
#575000
b1001111111100110 #
b1001111111100110 0
b1111001010111 "
b1111001010111 1
1%
#580000
b10011 +
0%
#585000
1%
#590000
b111101001110 /
b111101001110 8
b1011111011101111 $
b1011111011101111 ,
b1011111011101111 4
b11110101000001011111011000010111 7
b1101111010101101 &
b1101111010101101 -
b1101111010101101 5
b101110010011000 )
b101110010011000 .
1'
0%
#595000
b1111111000010101 /
b1111111000010101 8
b0 #
b0 0
b0 "
b0 1
b101110010011000 !
b101110010011000 3
b11110011111100100110001010111000 7
b101110010011000 2
b101110010011000 6
1%
#600000
b111001010010110 /
b111001010010110 8
b0 $
b0 ,
b0 4
b111001010010110110110111000 7
b1001111001101 &
b1001111001101 -
b1001111001101 5
b0 )
b0 .
0'
0%
#605000
b111001010010110 #
b111001010010110 0
b1001111001101 "
b1001111001101 1
1%
#610000
b10100 +
0%
#615000
1%
#620000
b1111111000010101 /
b1111111000010101 8
b1011111011101111 $
b1011111011101111 ,
b1011111011101111 4
b11110011111100100110001010111000 7
b1101111010101101 &
b1101111010101101 -
b1101111010101101 5
b11010001011110 )
b11010001011110 .
1'
0%
#625000
b101000111011101 /
b101000111011101 8
b0 #
b0 0
b0 "
b0 1
b11010001011110 !
b11010001011110 3
b11111001001011101110011110000110 7
b11010001011110 2
b11010001011110 6
1%
#630000
b1000001101110100 /
b1000001101110100 8
b0 $
b0 ,
b0 4
b11101000001101110100101010101010 7
b1000101110111011 &
b1000101110111011 -
b1000101110111011 5
b0 )
b0 .
0'
0%
#635000
b1000001101110100 #
b1000001101110100 0
b1000101110111011 "
b1000101110111011 1
1%
#640000
b10101 +
0%
#645000
1%
#650000
b101000111011101 /
b101000111011101 8
b1011111011101111 $
b1011111011101111 ,
b1011111011101111 4
b11111001001011101110011110000110 7
b1101111010101101 &
b1101111010101101 -
b1101111010101101 5
b1011101001010111 )
b1011101001010111 .
1'
0%
#655000
b101000000000100 /
b101000000000100 8
b0 #
b0 0
b0 "
b0 1
b1011101001010111 !
b1011101001010111 3
b1001000100010101111011001011 7
b1011101001010111 2
b1011101001010111 6
1%
#660000
b1110101010111110 /
b1110101010111110 8
b0 $
b0 ,
b0 4
b1110101010111110111100100011 7
b1100101000010101 &
b1100101000010101 -
b1100101000010101 5
b0 )
b0 .
0'
0%
#665000
b1110101010111110 #
b1110101010111110 0
b1100101000010101 "
b1100101000010101 1
1%
#670000
b10110 +
0%
#675000
1%
#680000
b101000000000100 /
b101000000000100 8
b1011111011101111 $
b1011111011101111 ,
b1011111011101111 4
b1001000100010101111011001011 7
b1101111010101101 &
b1101111010101101 -
b1101111010101101 5
b1001010001101101 )
b1001010001101101 .
1'
0%
#685000
b1001111011111100 /
b1001111011111100 8
b0 #
b0 0
b0 "
b0 1
b1001010001101101 !
b1001010001101101 3
b1110000000001101001110101001 7
b1001010001101101 2
b1001010001101101 6
1%
#690000
b1100101111101011 /
b1100101111101011 8
b0 $
b0 ,
b0 4
b11100101111101011111110111000 7
b1011101110011000 &
b1011101110011000 -
b1011101110011000 5
b0 )
b0 .
0'
0%
#695000
b1100101111101011 #
b1100101111101011 0
b1011101110011000 "
b1011101110011000 1
1%
#700000
b10111 +
0%
#705000
1%
#710000
b1001111011111100 /
b1001111011111100 8
b1011111011101111 $
b1011111011101111 ,
b1011111011101111 4
b1110000000001101001110101001 7
b1101111010101101 &
b1101111010101101 -
b1101111010101101 5
b1001100111011011 )
b1001100111011011 .
1'
0%
#715000
b1001001110101101 /
b1001001110101101 8
b0 #
b0 0
b0 "
b0 1
b1001100111011011 !
b1001100111011011 3
b1101010010111110001011111111 7
b1001100111011011 2
b1001100111011011 6
1%
#720000
b110101011011110 /
b110101011011110 8
b0 $
b0 ,
b0 4
b10110101011011110000100010011 7
b1100011100101001 &
b1100011100101001 -
b1100011100101001 5
b0 )
b0 .
0'
0%
#725000
b110101011011110 #
b110101011011110 0
b1100011100101001 "
b1100011100101001 1
1%
#730000
b11000 +
0%
#735000
1%
#740000
b1001001110101101 /
b1001001110101101 8
b1011111011101111 $
b1011111011101111 ,
b1011111011101111 4
b1101010010111110001011111111 7
b1101111010101101 &
b1101111010101101 -
b1101111010101101 5
b10001010111100 )
b10001010111100 .
1'
0%
#745000
b111011010010111 /
b111011010010111 8
b0 #
b0 0
b0 "
b0 1
b10001010111100 !
b10001010111100 3
b11111011011110101000000100001100 7
b10001010111100 2
b10001010111100 6
1%
#750000
b1011010011100000 /
b1011010011100000 8
b0 $
b0 ,
b0 4
b11111011010011100000000000101100 7
b1101110101100101 &
b1101110101100101 -
b1101110101100101 5
b0 )
b0 .
0'
0%
#755000
b1011010011100000 #
b1011010011100000 0
b1101110101100101 "
b1101110101100101 1
1%
#760000
b11001 +
0%
#765000
1%
#770000
b111011010010111 /
b111011010010111 8
b1011111011101111 $
b1011111011101111 ,
b1011111011101111 4
b11111011011110101000000100001100 7
b1101111010101101 &
b1101111010101101 -
b1101111010101101 5
b1101111011000100 )
b1101111011000100 .
1'
0%
#775000
b10000100111 /
b10000100111 8
b0 #
b0 0
b0 "
b0 1
b1101111011000100 !
b1101111011000100 3
b100010100111000001001110100 7
b1101111011000100 2
b1101111011000100 6
1%
#780000
b1001101001111000 /
b1001101001111000 8
b0 $
b0 ,
b0 4
b1001101001111000110000001000 7
b1011010110100010 &
b1011010110100010 -
b1011010110100010 5
b0 )
b0 .
0'
0%
#785000
b1001101001111000 #
b1001101001111000 0
b1011010110100010 "
b1011010110100010 1
1%
#790000
b11010 +
0%
#795000
1%
#800000
b10000100111 /
b10000100111 8
b1011111011101111 $
b1011111011101111 ,
b1011111011101111 4
b100010100111000001001110100 7
b1101111010101101 &
b1101111010101101 -
b1101111010101101 5
b1100010001011000 )
b1100010001011000 .
1'
0%
#805000
b11101100101110 /
b11101100101110 8
b0 #
b0 0
b0 "
b0 1
b1100010001011000 !
b1100010001011000 3
b111110000111111111101111000 7
b1100010001011000 2
b1100010001011000 6
1%
#810000
b101111100111000 /
b101111100111000 8
b0 $
b0 ,
b0 4
b11100101111100111000110011000000 7
b110111111001000 &
b110111111001000 -
b110111111001000 5
b0 )
b0 .
0'
0%
#815000
b101111100111000 #
b101111100111000 0
b110111111001000 "
b110111111001000 1
1%
#820000
b11011 +
0%
#825000
1%
#830000
b11101100101110 /
b11101100101110 8
b1011111011101111 $
b1011111011101111 ,
b1011111011101111 4
b111110000111111111101111000 7
b1101111010101101 &
b1101111010101101 -
b1101111010101101 5
b10010111100101 )
b10010111100101 .
1'
0%
#835000
b111000000000010 /
b111000000000010 8
b0 #
b0 0
b0 "
b0 1
b10010111100101 !
b10010111100101 3
b11111011000100010011000111000001 7
b10010111100101 2
b10010111100101 6
1%
#840000
b100001000101000 /
b100001000101000 8
b0 $
b0 ,
b0 4
b100001000101000011111001011 7
b1101111101111 &
b1101111101111 -
b1101111101111 5
b0 )
b0 .
0'
0%
#845000
b100001000101000 #
b100001000101000 0
b1101111101111 "
b1101111101111 1
1%
#850000
b11100 +
0%
#855000
1%
#860000
b111000000000010 /
b111000000000010 8
b1011111011101111 $
b1011111011101111 ,
b1011111011101111 4
b11111011000100010011000111000001 7
b1101111010101101 &
b1101111010101101 -
b1101111010101101 5
b1010101111010000 )
b1010101111010000 .
1'
0%
#865000
b110111001000110 /
b110111001000110 8
b0 #
b0 0
b0 "
b0 1
b1010101111010000 !
b1010101111010000 3
b1010111101010111101110010000 7
b1010101111010000 2
b1010101111010000 6
1%
#870000
b1100101101100011 /
b1100101101100011 8
b0 $
b0 ,
b0 4
b11101100101101100011010010110000 7
b11101010100111 &
b11101010100111 -
b11101010100111 5
b0 )
b0 .
0'
0%
#875000
b1100101101100011 #
b1100101101100011 0
b11101010100111 "
b11101010100111 1
1%
#880000
b11101 +
0%
#885000
1%
#890000
b110111001000110 /
b110111001000110 8
b1011111011101111 $
b1011111011101111 ,
b1011111011101111 4
b1010111101010111101110010000 7
b1101111010101101 &
b1101111010101101 -
b1101111010101101 5
b1010100111010101 )
b1010100111010101 .
1'
0%
#895000
b111001001100110 /
b111001001100110 8
b0 #
b0 0
b0 "
b0 1
b1010100111010101 !
b1010100111010101 3
b1011001101110111101011110001 7
b1010100111010101 2
b1010100111010101 6
1%
#900000
b1010011000110001 /
b1010011000110001 8
b0 $
b0 ,
b0 4
b1010011000110001011011110100 7
b1110000100100100 &
b1110000100100100 -
b1110000100100100 5
b0 )
b0 .
0'
0%
#905000
b1010011000110001 #
b1010011000110001 0
b1110000100100100 "
b1110000100100100 1
1%
#910000
b11110 +
0%
#915000
1%
#920000
b111001001100110 /
b111001001100110 8
b1011111011101111 $
b1011111011101111 ,
b1011111011101111 4
b1011001101110111101011110001 7
b1101111010101101 &
b1101111010101101 -
b1101111010101101 5
b111110101010000 )
b111110101010000 .
1'
0%
#925000
b1011100111101111 /
b1011100111101111 8
b0 #
b0 0
b0 "
b0 1
b111110101010000 !
b111110101010000 3
b11101111101100000000111100010000 7
b111110101010000 2
b111110101010000 6
1%
#930000
b1100010101011 /
b1100010101011 8
b0 $
b0 ,
b0 4
b10001100010101011000011100000 7
b10001111010110 &
b10001111010110 -
b10001111010110 5
b0 )
b0 .
0'
0%
#935000
b1100010101011 #
b1100010101011 0
b10001111010110 "
b10001111010110 1
1%
#940000
b11111 +
0%
#945000
1%
#950000
b1011100111101111 /
b1011100111101111 8
b1011111011101111 $
b1011111011101111 ,
b1011111011101111 4
b11101111101100000000111100010000 7
b1101111010101101 &
b1101111010101101 -
b1101111010101101 5
b111010010100 )
b111010010100 .
1'
0%
#955000
b1010000010010010 /
b1010000010010010 8
b0 #
b0 0
b0 "
b0 1
b111010010100 !
b111010010100 3
b11111110000110100011001000000100 7
b111010010100 2
b111010010100 6
1%
#960000
b10101100001110 /
b10101100001110 8
b0 $
b0 ,
b0 4
b10101100001110111000101000 7
b10111101000010 &
b10111101000010 -
b10111101000010 5
b0 )
b0 .
0'
0%
#965000
b10101100001110 #
b10101100001110 0
b10111101000010 "
b10111101000010 1
1%
#970000
b100000 +
0%
#975000
1%
