verilog_src/mac_q4_12.v
module mac_q4_12 (
    input wire signed [15:0] weight,
    input wire signed [15:0] in_val,
    input wire signed [15:0] acc_in,
    output reg signed [15:0] acc_out
);

    wire signed [31:0] product;

    assign product = weight * in_val;
    always @(*) begin
        acc_out = acc_in + product[27:12];
    end

endmodule

verilog_src/systolic_pe.v
`timescale 1ns / 1ps

module systolic_pe (
    input wire clk,
    input wire rst,
    input wire load_weight,
    input wire signed [15:0] weight_in,
    input wire signed [15:0] in_val_in,
    input wire signed [15:0] acc_in,

    output reg signed [15:0] weight_out,
    output reg signed [15:0] in_val_out,
    output reg signed [15:0] acc_out
);

    reg signed [15:0] stationary_weight;
    wire signed [15:0] mac_result;

    mac_q4_12 core_mac (
        .weight(stationary_weight),
        .in_val(in_val_in),
        .acc_in(acc_in),
        .acc_out(mac_result)
    );

    always @(posedge clk or posedge rst) begin
        if (rst) begin
            stationary_weight <= 16'd0;
            weight_out <= 16'd0;
            in_val_out <= 16'd0;
            acc_out    <= 16'd0;
        end else if (load_weight) begin
            stationary_weight <= weight_in;
            weight_out <= weight_in;
            in_val_out <= 16'd0;
            acc_out    <= 16'd0;
        end else begin
            in_val_out <= in_val_in;
            acc_out    <= mac_result;
        end
    end
endmodule

v1/verilog_src/tb_systolic_pe.v
`timescale 1ns / 1ps

module tb_systolic_pe;
    reg clk;
    reg rst;
    reg load_weight;
    reg signed [15:0] weight_in;
    reg signed [15:0] in_val_in;
    reg signed [15:0] acc_in;

    wire signed [15:0] weight_out;
    wire signed [15:0] in_val_out;
    wire signed [15:0] acc_out;

    reg signed [15:0] test_weights [0:99];
    reg signed [15:0] test_in_vals [0:99];
    reg signed [15:0] expected_outs [0:99];

    integer i;
    integer errors = 0;

    // Instantiate PE
    systolic_pe u_pe (
        .clk(clk),
        .rst(rst),
        .load_weight(load_weight),
        .weight_in(weight_in),
        .in_val_in(in_val_in),
        .acc_in(acc_in),
        .weight_out(weight_out),
        .in_val_out(in_val_out),
        .acc_out(acc_out)
    );

    // Clock generation (10ns period)
    initial begin
        clk = 0;
        forever #5 clk = ~clk;
    end

    initial begin
        // Waveform dump for debugging
        $dumpfile("tb_pe.vcd");
        $dumpvars(0, tb_systolic_pe);

        // Load vectors
        $readmemh("pe_weights.hex", test_weights);
        $readmemh("pe_in_vals.hex", test_in_vals);
        $readmemh("pe_expected_outs.hex", expected_outs);

        // Initialize inputs
        rst = 1;
        load_weight = 0;
        weight_in = 0;
        in_val_in = 0;
        acc_in = 0;

        $display("----------------------------------------");
        $display("Starting Cycle-Accurate PE Test...");
        $display("----------------------------------------");

        // Cycle 0: Reset pulse
        @(negedge clk);
        rst = 0;

        for (i = 0; i < 100; i = i + 1) begin
            // Progress marker
            if (i % 20 == 0) $display("  ...vector %0d", i);

            // Cycle 1: Load Phase
            @(negedge clk);
            load_weight = 1;
            weight_in = test_weights[i];
            in_val_in = 16'hDEAD; // Drive garbage to prove load flush works
            acc_in = 16'hBEEF;    // Drive garbage

            // Cycle 2: Compute Phase (Inputs presented)
            @(negedge clk);
            load_weight = 0;
            weight_in = 16'h0000;
            in_val_in = test_in_vals[i];
            acc_in = 16'd0; // Standalone PE, no accumulation

            // Cycle 3: Check Result (after rising edge has latched it)
            @(negedge clk);
            if (acc_out !== expected_outs[i]) begin
                $display("FAIL at vector %0d: W=%h, X=%h", i, test_weights[i], test_in_vals[i]);
                $display("  Expected %h, Got %h", expected_outs[i], acc_out);
                errors = errors + 1;
            end
        end

        $display("----------------------------------------");
        if (errors == 0)
            $display("PASS: PE Timing and Math verified for 100 cycles!");
        else
            $display("FAIL: %0d errors found.", errors);
        $display("----------------------------------------");

        $finish;
    end
endmodule

v1/verilog_src/tb_pe.vcd
$date
	Mon Sep 14 15:08:27 2026
$end
$version
	Icarus Verilog
$end
$timescale
	1ps
$end
$scope module tb_systolic_pe $end
$var wire 16 ! weight_out [15:0] $end
$var wire 16 " in_val_out [15:0] $end
$var wire 16 # acc_out [15:0] $end
$var reg 16 $ acc_in [15:0] $end
$var reg 1 % clk $end
$var reg 16 & in_val_in [15:0] $end
$var reg 1 ' load_weight $end
$var reg 1 ( rst $end
$var reg 16 ) weight_in [15:0] $end
$var integer 32 * errors [31:0] $end
$var integer 32 + i [31:0] $end
$scope module u_pe $end
$var wire 16 , acc_in [15:0] $end
$var wire 1 % clk $end
$var wire 16 - in_val_in [15:0] $end
$var wire 1 ' load_weight $end
$var wire 1 ( rst $end
$var wire 16 . weight_in [15:0] $end
$var wire 16 / mac_result [15:0] $end
$var reg 16 0 acc_out [15:0] $end
$var reg 16 1 in_val_out [15:0] $end
$var reg 16 2 stationary_weight [15:0] $end
$var reg 16 3 weight_out [15:0] $end
$scope module core_mac $end
$var wire 16 4 acc_in [15:0] $end
$var wire 16 5 in_val [15:0] $end
$var wire 16 6 weight [15:0] $end
$var wire 32 7 product [31:0] $end
$var reg 16 8 acc_out [15:0] $end
$upscope $end
$upscope $end
$upscope $end
$enddefinitions $end
$comment Show the parameter values. $end
$dumpall
$end
#0
$dumpvars
b0 8
b0 7
b0 6
b0 5
b0 4
b0 3
b0 2
b0 1
b0 0
b0 /
b0 .
b0 -
b0 ,
bx +
b0 *
b0 )
1(
0'
b0 &
0%
b0 $
b0 #
b0 "
b0 !
$end
#5000
1%
#10000
b0 +
0(
0%
#15000
1%
#20000
b1011111011101111 /
b1011111011101111 8
b1011111011101111 $
b1011111011101111 ,
b1011111011101111 4
b1101111010101101 &
b1101111010101101 -
b1101111010101101 5
b1000111010 )
b1000111010 .
1'
0%
#25000
b111010010111100 /
b111010010111100 8
b1000111010 !
b1000111010 3
b11111111101101011100110100110010 7
b1000111010 2
b1000111010 6
1%
#30000
b1110111100010011 /
b1110111100010011 8
b0 $
b0 ,
b0 4
b11111111111011110001001100011100 7
b1111100001100110 &
b1111100001100110 -
b1111100001100110 5
b0 )
b0 .
0'
0%
#35000
b1110111100010011 #
b1110111100010011 0
b1111100001100110 "
b1111100001100110 1
1%
#40000
b1 +
0%
#45000
1%
#50000
b111010010111100 /
b111010010111100 8
b1011111011101111 $
b1011111011101111 ,
b1011111011101111 4
b11111111101101011100110100110010 7
b1101111010101101 &
b1101111010101101 -
b1101111010101101 5
b1111110001100110 )
b1111110001100110 .
1'
0%
#55000
b11011011110011 /
b11011011110011 8
b0 #
b0 0
b0 "
b0 1
b1111110001100110 !
b1111110001100110 3
b11110000000010011101110 7
b1111110001100110 2
b1111110001100110 6
1%
#60000
b111111110100 /
b111111110100 8
b0 $
b0 ,
b0 4
b11111111010000101100 7
b1111101110010010 &
b1111101110010010 -
b1111101110010010 5
b0 )
b0 .
0'
0%
#65000
b111111110100 #
b111111110100 0
b1111101110010010 "
b1111101110010010 1
1%
#70000
b10 +
0%
#75000
1%
#80000
b11011011110011 /
b11011011110011 8
b1011111011101111 $
b1011111011101111 ,
b1011111011101111 4
b11110000000010011101110 7
b1101111010101101 &
b1101111010101101 -
b1101111010101101 5
b1111001000 )
b1111001000 .
1'
0%
#85000
b100000011101101 /
b100000011101101 8
b0 #
b0 0
b0 "
b0 1
b1111001000 !
b1111001000 3
b11111111100000011111111000101000 7
b1111001000 2
b1111001000 6
1%
#90000
b101010101101 /
b101010101101 8
b0 $
b0 ,
b0 4
b10101010110111011000 7
b1011010011 &
b1011010011 -
b1011010011 5
b0 )
b0 .
0'
0%
#95000
b101010101101 #
b101010101101 0
b1011010011 "
b1011010011 1
1%
#100000
b11 +
0%
#105000
1%
#110000
b100000011101101 /
b100000011101101 8
b1011111011101111 $
b1011111011101111 ,
b1011111011101111 4
b11111111100000011111111000101000 7
b1101111010101101 &
b1101111010101101 -
b1101111010101101 5
b11001000101 )
b11001000101 .
1'
0%
#115000
b1110111000000001 /
b1110111000000001 8
b0 #
b0 0
b0 "
b0 1
b11001000101 !
b11001000101 3
b11111111001011110001001010100001 7
b11001000101 2
b11001000101 6
1%
#120000
b1101011010001111 /
b1101011010001111 8
b0 $
b0 ,
b0 4
b11111111110101101000111111110100 7
b1111100101100100 &
b1111100101100100 -
b1111100101100100 5
b0 )
b0 .
0'
0%
#125000
b1101011010001111 #
b1101011010001111 0
b1111100101100100 "
b1111100101100100 1
1%
#130000
b100 +
0%
#135000
1%
#140000
b1110111000000001 /
b1110111000000001 8
b1011111011101111 $
b1011111011101111 ,
b1011111011101111 4
b11111111001011110001001010100001 7
b1101111010101101 &
b1101111010101101 -
b1101111010101101 5
b1111111011000000 )
b1111111011000000 .
1'
0%
#145000
b1110100010010110 /
b1110100010010110 8
b0 #
b0 0
b0 "
b0 1
b1111111011000000 !
b1111111011000000 3
b1010011010011111000000 7
b1111111011000000 2
b1111111011000000 6
1%
#150000
b100101100111 /
b100101100111 8
b0 $
b0 ,
b0 4
b10010110011110000000 7
b1111100001111010 &
b1111100001111010 -
b1111100001111010 5
b0 )
b0 .
0'
0%
#155000
b100101100111 #
b100101100111 0
b1111100001111010 "
b1111100001111010 1
1%
#160000
b101 +
0%
#165000
1%
#170000
b1110100010010110 /
b1110100010010110 8
b1011111011101111 $
b1011111011101111 ,
b1011111011101111 4
b1010011010011111000000 7
b1101111010101101 &
b1101111010101101 -
b1101111010101101 5
b1111101101111111 )
b1111101101111111 .
1'
0%
#175000
b101010100000101 /
b101010100000101 8
b0 #
b0 0
b0 "
b0 1
b1111101101111111 !
b1111101101111111 3
b100101100001011011010011 7
b1111101101111111 2
b1111101101111111 6
1%
#180000
b1111111110100001 /
b1111111110100001 8
b0 $
b0 ,
b0 4
b11111111111111111010000101101011 7
b10101 &
b10101 -
b10101 5
b0 )
b0 .
0'
0%
#185000
b1111111110100001 #
b1111111110100001 0
b10101 "
b10101 1
1%
#190000
b110 +
0%
#195000
1%
#200000
b101010100000101 /
b101010100000101 8
b1011111011101111 $
b1011111011101111 ,
b1011111011101111 4
b100101100001011011010011 7
b1101111010101101 &
b1101111010101101 -
b1101111010101101 5
b1111100001101101 )
b1111100001101101 .
1'
0%
#205000
b1011101101010110 /
b1011101101010110 8
b0 #
b0 0
b0 "
b0 1
b1111100001101101 !
b1111100001101101 3
b111111000110011110101001 7
b1111100001101101 2
b1111100001101101 6
1%
#210000
b10010010000010 /
b10010010000010 8
b0 $
b0 ,
b0 4
b1001001000001010010110 7
b1111101100101110 &
b1111101100101110 -
b1111101100101110 5
b0 )
b0 .
0'
0%
#215000
b10010010000010 #
b10010010000010 0
b1111101100101110 "
b1111101100101110 1
1%
#220000
b111 +
0%
#225000
1%
#230000
b1011101101010110 /
b1011101101010110 8
b1011111011101111 $
b1011111011101111 ,
b1011111011101111 4
b111111000110011110101001 7
b1101111010101101 &
b1101111010101101 -
b1101111010101101 5
b1001100101 )
b1001100101 .
1'
0%
#235000
b110111100100011 /
b110111100100011 8
b0 #
b0 0
b0 "
b0 1
b1001100101 !
b1001100101 3
b11111111101100000011010001000001 7
b1001100101 2
b1001100101 6
1%
#240000
b110111000 /
b110111000 8
b0 $
b0 ,
b0 4
b11011100010011000 7
b10111000 &
b10111000 -
b10111000 5
b0 )
b0 .
0'
0%
#245000
b110111000 #
b110111000 0
b10111000 "
b10111000 1
1%
#250000
b1000 +
0%
#255000
1%
#260000
b110111100100011 /
b110111100100011 8
b1011111011101111 $
b1011111011101111 ,
b1011111011101111 4
b11111111101100000011010001000001 7
b1101111010101101 &
b1101111010101101 -
b1101111010101101 5
b1111101110000111 )
b1111101110000111 .
1'
0%
#265000
b101001111111011 /
b101001111111011 8
b0 #
b0 0
b0 "
b0 1
b1111101110000111 !
b1111101110000111 3
b100101010000110000111011 7
b1111101110000111 2
b1111101110000111 6
1%
#270000
b1111100110011111 /
b1111100110011111 8
b0 $
b0 ,
b0 4
b11111111111110011001111101111011 7
b101101101 &
b101101101 -
b101101101 5
b0 )
b0 .
0'
0%
#275000
b1111100110011111 #
b1111100110011111 0
b101101101 "
b101101101 1
1%
#280000
b1001 +
0%
#285000
1%
#290000
b101001111111011 /
b101001111111011 8
b1011111011101111 $
b1011111011101111 ,
b1011111011101111 4
b100101010000110000111011 7
b1101111010101101 &
b1101111010101101 -
b1101111010101101 5
b10011110011 )
b10011110011 .
1'
0%
#295000
b1101000000001 /
b1101000000001 8
b0 #
b0 0
b0 "
b0 1
b10011110011 !
b10011110011 3
b11111111010110110001001000110111 7
b10011110011 2
b10011110011 6
1%
#300000
b1101100011101101 /
b1101100011101101 8
b0 $
b0 ,
b0 4
b11111111110110001110110110100001 7
b1111100000011011 &
b1111100000011011 -
b1111100000011011 5
b0 )
b0 .
0'
0%
#305000
b1101100011101101 #
b1101100011101101 0
b1111100000011011 "
b1111100000011011 1
1%
#310000
b1010 +
0%
#315000
1%
#320000
b1101000000001 /
b1101000000001 8
b1011111011101111 $
b1011111011101111 ,
b1011111011101111 4
b11111111010110110001001000110111 7
b1101111010101101 &
b1101111010101101 -
b1101111010101101 5
b10011100100 )
b10011100100 .
1'
0%
#325000
b1101111110101 /
b1101111110101 8
b0 #
b0 0
b0 "
b0 1
b10011100100 !
b10011100100 3
b11111111010111010000011000010100 7
b10011100100 2
b10011100100 6
1%
#330000
b111101111110 /
b111101111110 8
b0 $
b0 ,
b0 4
b11110111111001001100 7
b1100101011 &
b1100101011 -
b1100101011 5
b0 )
b0 .
0'
0%
#335000
b111101111110 #
b111101111110 0
b1100101011 "
b1100101011 1
1%
#340000
b1011 +
0%
#345000
1%
#350000
b1101111110101 /
b1101111110101 8
b1011111011101111 $
b1011111011101111 ,
b1011111011101111 4
b11111111010111010000011000010100 7
b1101111010101101 &
b1101111010101101 -
b1101111010101101 5
b1111110101110001 )
b1111110101110001 .
1'
0%
#355000
b1010000110010 /
b1010000110010 8
b0 #
b0 0
b0 "
b0 1
b1111110101110001 !
b1111110101110001 3
b10101010100001101011101 7
b1111110101110001 2
b1111110101110001 6
1%
#360000
b111000011010 /
b111000011010 8
b0 $
b0 ,
b0 4
b11100001101000101101 7
b1111101001111101 &
b1111101001111101 -
b1111101001111101 5
b0 )
b0 .
0'
0%
#365000
b111000011010 #
b111000011010 0
b1111101001111101 "
b1111101001111101 1
1%
#370000
b1100 +
0%
#375000
1%
#380000
b1010000110010 /
b1010000110010 8
b1011111011101111 $
b1011111011101111 ,
b1011111011101111 4
b10101010100001101011101 7
b1101111010101101 &
b1101111010101101 -
b1101111010101101 5
b11101010000 )
b11101010000 .
1'
0%
#385000
b1100101101000000 /
b1100101101000000 8
b0 #
b0 0
b0 "
b0 1
b11101010000 !
b11101010000 3
b11111111000011000101000100010000 7
b11101010000 2
b11101010000 6
1%
#390000
b1110110011011100 /
b1110110011011100 8
b0 $
b0 ,
b0 4
b11111111111011001101110010100000 7
b1111110101100010 &
b1111110101100010 -
b1111110101100010 5
b0 )
b0 .
0'
0%
#395000
b1110110011011100 #
b1110110011011100 0
b1111110101100010 "
b1111110101100010 1
1%
#400000
b1101 +
0%
#405000
1%
#410000
b1100101101000000 /
b1100101101000000 8
b1011111011101111 $
b1011111011101111 ,
b1011111011101111 4
b11111111000011000101000100010000 7
b1101111010101101 &
b1101111010101101 -
b1101111010101101 5
b1111100101111100 )
b1111100101111100 .
1'
0%
#415000
b1001100000001111 /
b1001100000001111 8
b0 #
b0 0
b0 "
b0 1
b1111100101111100 !
b1111100101111100 3
b110110010010000011001100 7
b1111100101111100 2
b1111100101111100 6
1%
#420000
b10101000001011 /
b10101000001011 8
b0 $
b0 ,
b0 4
b1010100000101111010000 7
b1111100110001100 &
b1111100110001100 -
b1111100110001100 5
b0 )
b0 .
0'
0%
#425000
b10101000001011 #
b10101000001011 0
b1111100110001100 "
b1111100110001100 1
1%
#430000
b1110 +
0%
#435000
1%
#440000
b1001100000001111 /
b1001100000001111 8
b1011111011101111 $
b1011111011101111 ,
b1011111011101111 4
b110110010010000011001100 7
b1101111010101101 &
b1101111010101101 -
b1101111010101101 5
b10110001110 )
b10110001110 .
1'
0%
#445000
b10111010011 /
b10111010011 8
b0 #
b0 0
b0 "
b0 1
b10110001110 !
b10110001110 3
b11111111010001101110010011110110 7
b10110001110 2
b10110001110 6
1%
#450000
b100100110011 /
b100100110011 8
b0 $
b0 ,
b0 4
b10010011001100110000 7
b110101000 &
b110101000 -
b110101000 5
b0 )
b0 .
0'
0%
#455000
b100100110011 #
b100100110011 0
b110101000 "
b110101000 1
1%
#460000
b1111 +
0%
#465000
1%
#470000
b10111010011 /
b10111010011 8
b1011111011101111 $
b1011111011101111 ,
b1011111011101111 4
b11111111010001101110010011110110 7
b1101111010101101 &
b1101111010101101 -
b1101111010101101 5
b10011101001 )
b10011101001 .
1'
0%
#475000
b1101101001110 /
b1101101001110 8
b0 #
b0 0
b0 "
b0 1
b10011101001 !
b10011101001 3
b11111111010111000101111101110101 7
b10011101001 2
b10011101001 6
1%
#480000
b1001000000111 /
b1001000000111 8
b0 $
b0 ,
b0 4
b100100000011110001100 7
b1110101100 &
b1110101100 -
b1110101100 5
b0 )
b0 .
0'
0%
#485000
b1001000000111 #
b1001000000111 0
b1110101100 "
b1110101100 1
1%
#490000
b10000 +
0%
#495000
1%
#500000
b1101101001110 /
b1101101001110 8
b1011111011101111 $
b1011111011101111 ,
b1011111011101111 4
b11111111010111000101111101110101 7
b1101111010101101 &
b1101111010101101 -
b1101111010101101 5
b10010100 )
b10010100 .
1'
0%
#505000
b1010101110101011 /
b1010101110101011 8
b0 #
b0 0
b0 "
b0 1
b10010100 !
b10010100 3
b11111111111011001011110000000100 7
b10010100 2
b10010100 6
1%
#510000
b10001011111 /
b10001011111 8
b0 $
b0 ,
b0 4
b1000101111111010100 7
b11110010001 &
b11110010001 -
b11110010001 5
b0 )
b0 .
0'
0%
#515000
b10001011111 #
b10001011111 0
b11110010001 "
b11110010001 1
1%
#520000
b10001 +
0%
#525000
1%
#530000
b1010101110101011 /
b1010101110101011 8
b1011111011101111 $
b1011111011101111 ,
b1011111011101111 4
b11111111111011001011110000000100 7
b1101111010101101 &
b1101111010101101 -
b1101111010101101 5
b1111111000001110 )
b1111111000001110 .
1'
0%
#535000
b1111111111000010 /
b1111111111000010 8
b0 #
b0 0
b0 "
b0 1
b1111111000001110 !
b1111111000001110 3
b10000001101001101110110 7
b1111111000001110 2
b1111111000001110 6
1%
#540000
b1111111001100001 /
b1111111001100001 8
b0 $
b0 ,
b0 4
b11111111111111100110000110100110 7
b11010101 &
b11010101 -
b11010101 5
b0 )
b0 .
0'
0%
#545000
b1111111001100001 #
b1111111001100001 0
b11010101 "
b11010101 1
1%
#550000
b10010 +
0%
#555000
1%
#560000
b1111111111000010 /
b1111111111000010 8
b1011111011101111 $
b1011111011101111 ,
b1011111011101111 4
b10000001101001101110110 7
b1101111010101101 &
b1101111010101101 -
b1101111010101101 5
b10101000100 )
b10101000100 .
1'
0%
#565000
b111101110101 /
b111101110101 8
b0 #
b0 0
b0 "
b0 1
b10101000100 !
b10101000100 3
b11111111010100001000011011110100 7
b10101000100 2
b10101000100 6
1%
#570000
b100111111001 /
b100111111001 8
b0 $
b0 ,
b0 4
b10011111100111010100 7
b111100101 &
b111100101 -
b111100101 5
b0 )
b0 .
0'
0%
#575000
b100111111001 #
b100111111001 0
b111100101 "
b111100101 1
1%
#580000
b10011 +
0%
#585000
1%
#590000
b111101110101 /
b111101110101 8
b1011111011101111 $
b1011111011101111 ,
b1011111011101111 4
b11111111010100001000011011110100 7
b1101111010101101 &
b1101111010101101 -
b1101111010101101 5
b10111001001 )
b10111001001 .
1'
0%
#595000
b1111111000100101 /
b1111111000100101 8
b0 #
b0 0
b0 "
b0 1
b10111001001 !
b10111001001 3
b11111111001111110011011011010101 7
b10111001001 2
b10111001001 6
1%
#600000
b11100100100 /
b11100100100 8
b0 $
b0 ,
b0 4
b1110010010000011100 7
b100111100 &
b100111100 -
b100111100 5
b0 )
b0 .
0'
0%
#605000
b11100100100 #
b11100100100 0
b100111100 "
b100111100 1
1%
#610000
b10100 +
0%
#615000
1%
#620000
b1111111000100101 /
b1111111000100101 8
b1011111011101111 $
b1011111011101111 ,
b1011111011101111 4
b11111111001111110011011011010101 7
b1101111010101101 &
b1101111010101101 -
b1101111010101101 5
b1101000101 )
b1101000101 .
1'
0%
#625000
b101000111111010 /
b101000111111010 8
b0 #
b0 0
b0 "
b0 1
b1101000101 !
b1101000101 3
b11111111100100110000101110100001 7
b1101000101 2
b1101000101 6
1%
#630000
b1110100000111110 /
b1110100000111110 8
b0 $
b0 ,
b0 4
b11111111111010000011111010101100 7
b1111100010111100 &
b1111100010111100 -
b1111100010111100 5
b0 )
b0 .
0'
0%
#635000
b1110100000111110 #
b1110100000111110 0
b1111100010111100 "
b1111100010111100 1
1%
#640000
b10101 +
0%
#645000
1%
#650000
b101000111111010 /
b101000111111010 8
b1011111011101111 $
b1011111011101111 ,
b1011111011101111 4
b11111111100100110000101110100001 7
b1101111010101101 &
b1101111010101101 -
b1101111010101101 5
b1111101110100101 )
b1111101110100101 .
1'
0%
#655000
b101000000010011 /
b101000000010011 8
b0 #
b0 0
b0 "
b0 1
b1111101110100101 !
b1111101110100101 3
b100100010010010010000001 7
b1111101110100101 2
b1111101110100101 6
1%
#660000
b111010101110 /
b111010101110 8
b0 $
b0 ,
b0 4
b11101010111011000101 7
b1111110010100001 &
b1111110010100001 -
b1111110010100001 5
b0 )
b0 .
0'
0%
#665000
b111010101110 #
b111010101110 0
b1111110010100001 "
b1111110010100001 1
1%
#670000
b10110 +
0%
#675000
1%
#680000
b101000000010011 /
b101000000010011 8
b1011111011101111 $
b1011111011101111 ,
b1011111011101111 4
b100100010010010010000001 7
b1101111010101101 &
b1101111010101101 -
b1101111010101101 5
b1111100101000111 )
b1111100101000111 .
1'
0%
#685000
b1001111011110101 /
b1001111011110101 8
b0 #
b0 0
b0 "
b0 1
b1111100101000111 !
b1111100101000111 3
b111000000000011011111011 7
b1111100101000111 2
b1111100101000111 6
1%
#690000
b1110011000001 /
b1110011000001 8
b0 $
b0 ,
b0 4
b111001100000101001111 7
b1111101110111001 &
b1111101110111001 -
b1111101110111001 5
b0 )
b0 .
0'
0%
#695000
b1110011000001 #
b1110011000001 0
b1111101110111001 "
b1111101110111001 1
1%
#700000
b10111 +
0%
#705000
1%
#710000
b1001111011110101 /
b1001111011110101 8
b1011111011101111 $
b1011111011101111 ,
b1011111011101111 4
b111000000000011011111011 7
b1101111010101101 &
b1101111010101101 -
b1101111010101101 5
b1111100110011110 )
b1111100110011110 .
1'
0%
#715000
b1001001110100010 /
b1001001110100010 8
b0 #
b0 0
b0 "
b0 1
b1111100110011110 !
b1111100110011110 3
b110101001011001111000110 7
b1111100110011110 2
b1111100110011110 6
1%
#720000
b1011010110000 /
b1011010110000 8
b0 $
b0 ,
b0 4
b101101011000001011100 7
b1111110001110010 &
b1111110001110010 -
b1111110001110010 5
b0 )
b0 .
0'
0%
#725000
b1011010110000 #
b1011010110000 0
b1111110001110010 "
b1111110001110010 1
1%
#730000
b11000 +
0%
#735000
1%
#740000
b1001001110100010 /
b1001001110100010 8
b1011111011101111 $
b1011111011101111 ,
b1011111011101111 4
b110101001011001111000110 7
b1101111010101101 &
b1101111010101101 -
b1101111010101101 5
b1000101011 )
b1000101011 .
1'
0%
#745000
b111011010110000 /
b111011010110000 8
b0 #
b0 0
b0 "
b0 1
b1000101011 !
b1000101011 3
b11111111101101111100000100001111 7
b1000101011 2
b1000101011 6
1%
#750000
b1111101101001110 /
b1111101101001110 8
b0 $
b0 ,
b0 4
b11111111111110110100111011110010 7
b1111110111010110 &
b1111110111010110 -
b1111110111010110 5
b0 )
b0 .
0'
0%
#755000
b1111101101001110 #
b1111101101001110 0
b1111110111010110 "
b1111110111010110 1
1%
#760000
b11001 +
0%
#765000
1%
#770000
b111011010110000 /
b111011010110000 8
b1011111011101111 $
b1011111011101111 ,
b1011111011101111 4
b11111111101101111100000100001111 7
b1101111010101101 &
b1101111010101101 -
b1101111010101101 5
b1111110111101100 )
b1111110111101100 .
1'
0%
#775000
b10000101111 /
b10000101111 8
b0 #
b0 0
b0 "
b0 1
b1111110111101100 !
b1111110111101100 3
b10001010100000001111100 7
b1111110111101100 2
b1111110111101100 6
1%
#780000
b100110101000 /
b100110101000 8
b0 $
b0 ,
b0 4
b10011010100011111000 7
b1111101101011010 &
b1111101101011010 -
b1111101101011010 5
b0 )
b0 .
0'
0%
#785000
b100110101000 #
b100110101000 0
b1111101101011010 "
b1111101101011010 1
1%
#790000
b11010 +
0%
#795000
1%
#800000
b10000101111 /
b10000101111 8
b1011111011101111 $
b1011111011101111 ,
b1011111011101111 4
b10001010100000001111100 7
b1101111010101101 &
b1101111010101101 -
b1101111010101101 5
b1111110001000101 )
b1111110001000101 .
1'
0%
#805000
b11101100111111 /
b11101100111111 8
b0 #
b0 0
b0 "
b0 1
b1111110001000101 !
b1111110001000101 3
b11111000101000010100001 7
b1111110001000101 2
b1111110001000101 6
1%
#810000
b1110010111110001 /
b1110010111110001 8
b0 $
b0 ,
b0 4
b11111111111001011111000111101100 7
b11011111100 &
b11011111100 -
b11011111100 5
b0 )
b0 .
0'
0%
#815000
b1110010111110001 #
b1110010111110001 0
b11011111100 "
b11011111100 1
1%
#820000
b11011 +
0%
#825000
1%
#830000
b11101100111111 /
b11101100111111 8
b1011111011101111 $
b1011111011101111 ,
b1011111011101111 4
b11111000101000010100001 7
b1101111010101101 &
b1101111010101101 -
b1101111010101101 5
b1001011110 )
b1001011110 .
1'
0%
#835000
b111000000001100 /
b111000000001100 8
b0 #
b0 0
b0 "
b0 1
b1001011110 !
b1001011110 3
b11111111101100010001110110000110 7
b1001011110 2
b1001011110 6
1%
#840000
b10000011111 /
b10000011111 8
b0 $
b0 ,
b0 4
b1000001111111000100 7
b110111110 &
b110111110 -
b110111110 5
b0 )
b0 .
0'
0%
#845000
b10000011111 #
b10000011111 0
b110111110 "
b110111110 1
1%
#850000
b11100 +
0%
#855000
1%
#860000
b111000000001100 /
b111000000001100 8
b1011111011101111 $
b1011111011101111 ,
b1011111011101111 4
b11111111101100010001110110000110 7
b1101111010101101 &
b1101111010101101 -
b1101111010101101 5
b1111101010111101 )
b1111101010111101 .
1'
0%
#865000
b110111001000110 /
b110111001000110 8
b0 #
b0 0
b0 "
b0 1
b1111101010111101 !
b1111101010111101 3
b101011110101011110111001 7
b1111101010111101 2
b1111101010111101 6
1%
#870000
b1110110010111000 /
b1110110010111000 8
b0 $
b0 ,
b0 4
b11111111111011001011100010000010 7
b1110101010 &
b1110101010 -
b1110101010 5
b0 )
b0 .
0'
0%
#875000
b1110110010111000 #
b1110110010111000 0
b1110101010 "
b1110101010 1
1%
#880000
b11101 +
0%
#885000
1%
#890000
b110111001000110 /
b110111001000110 8
b1011111011101111 $
b1011111011101111 ,
b1011111011101111 4
b101011110101011110111001 7
b1101111010101101 &
b1101111010101101 -
b1101111010101101 5
b1111101010011101 )
b1111101010011101 .
1'
0%
#895000
b111001001110001 /
b111001001110001 8
b0 #
b0 0
b0 "
b0 1
b1111101010011101 !
b1111101010011101 3
b101100111000001000011001 7
b1111101010011101 2
b1111101010011101 6
1%
#900000
b101001100101 /
b101001100101 8
b0 $
b0 ,
b0 4
b10100110010100001010 7
b1111111000010010 &
b1111111000010010 -
b1111111000010010 5
b0 )
b0 .
0'
0%
#905000
b101001100101 #
b101001100101 0
b1111111000010010 "
b1111111000010010 1
1%
#910000
b11110 +
0%
#915000
1%
#920000
b111001001110001 /
b111001001110001 8
b1011111011101111 $
b1011111011101111 ,
b1011111011101111 4
b101100111000001000011001 7
b1101111010101101 &
b1101111010101101 -
b1101111010101101 5
b11111010100 )
b11111010100 .
1'
0%
#925000
b1011101000010001 /
b1011101000010001 8
b0 #
b0 0
b0 "
b0 1
b11111010100 !
b11111010100 3
b11111110111110110010001001000100 7
b11111010100 2
b11111010100 6
1%
#930000
b1000110000101 /
b1000110000101 8
b0 $
b0 ,
b0 4
b100011000010110000100 7
b1000111101 &
b1000111101 -
b1000111101 5
b0 )
b0 .
0'
0%
#935000
b1000110000101 #
b1000110000101 0
b1000111101 "
b1000111101 1
1%
#940000
b11111 +
0%
#945000
1%
#950000
b1011101000010001 /
b1011101000010001 8
b1011111011101111 $
b1011111011101111 ,
b1011111011101111 4
b11111110111110110010001001000100 7
b1101111010101101 &
b1101111010101101 -
b1101111010101101 5
b11101001 )
b11101001 .
1'
0%
#955000
b1010000010011010 /
b1010000010011010 8
b0 #
b0 0
b0 "
b0 1
b11101001 !
b11101001 3
b11111111111000011010101101110101 7
b11101001 2
b11101001 6
1%
#960000
b1010101111 /
b1010101111 8
b0 $
b0 ,
b0 4
b101010111100101011 7
b1011110011 &
b1011110011 -
b1011110011 5
b0 )
b0 .
0'
0%
#965000
b1010101111 #
b1010101111 0
b1011110011 "
b1011110011 1
1%
#970000
b100000 +
0%
#975000
1%
#980000
b1010000010011010 /
b1010000010011010 8
b1011111011101111 $
b1011111011101111 ,
b1011111011101111 4
b11111111111000011010101101110101 7
b1101111010101101 &
b1101111010101101 -
b1101111010101101 5
b10101111011 )
b10101111011 .
1'
0%
#985000
b100001001101 /
b100001001101 8
b0 #
b0 0
b0 "
b0 1
b10101111011 !
b10101111011 3
b11111111010010010101111000011111 7
b10101111011 2
b10101111011 6
1%
#990000
b1100000110000 /
b1100000110000 8
b0 $
b0 ,
b0 4
b110000011000011101110 7
b10001101010 &
b10001101010 -
b10001101010 5
b0 )
b0 .
0'
0%
#995000
b1100000110000 #
b1100000110000 0
b10001101010 "
b10001101010 1
1%
#1000000
b100001 +
0%
#1005000
1%
#1010000
b100001001101 /
b100001001101 8
b1011111011101111 $
b1011111011101111 ,
b1011111011101111 4
b11111111010010010101111000011111 7
b1101111010101101 &
b1101111010101101 -
b1101111010101101 5
b1111101110101010 )
b1111101110101010 .
1'
0%
